gunc/__init__.py
gunc/_version.py
gunc/checkm_merge.py
gunc/external_tools.py
gunc/get_scores.py
gunc/gunc.py
gunc/gunc_database.py
gunc/visualisation.py
gunc/data/genome2taxonomy_gtdbref.tsv
gunc/data/genome2taxonomy_ref.tsv
gunc/data/template.html
gunc/tests/__init__.py
gunc/tests/test_external_tools.py
gunc/tests/test_get_scores.py
gunc/tests/test_gunc.py
gunc/tests/test_gunc_database.py
gunc/tests/test_visualisation.py
gunc-1.0.6.dist-info/AUTHORS.rst
gunc-1.0.6.dist-info/LICENSE
gunc-1.0.6.dist-info/METADATA
gunc-1.0.6.dist-info/WHEEL
gunc-1.0.6.dist-info/entry_points.txt
gunc-1.0.6.dist-info/top_level.txt
gunc-1.0.6.dist-info/RECORD
