Metadata-Version: 2.1
Name: gunc
Version: 1.0.6
Summary: Python package for detection of chimerism and contamination in prokaryotic genomes.
Home-page: https://github.com/grp-bork/gunc
Author: Anthony Fullam
Author-email: anthony.fullam@embl.de
License: BSD (3-clause)
Platform: UNKNOWN
Classifier: Environment :: Console
Classifier: Natural Language :: English
Classifier: Development Status :: 4 - Beta
Classifier: Programming Language :: Python :: 3
Classifier: Intended Audience :: Science/Research
Classifier: Topic :: Scientific/Engineering :: Bio-Informatics
Classifier: License :: OSI Approved :: GNU General Public License v3 or later (GPLv3+)
Requires-Python: >=3.6
Requires-Dist: numpy
Requires-Dist: scipy
Requires-Dist: pandas (>=2.0.0)
Requires-Dist: plotly
Requires-Dist: requests (>=2.22.0)
